ShiyanlouPythonJiaochengHeji20160905Fix1/README.md
ShiyanlouPythonJiaochengHeji20160905Fix1/__init__.py
ShiyanlouPythonJiaochengHeji20160905Fix1/__main__.py
ShiyanlouPythonJiaochengHeji20160905Fix1/file.epub
ShiyanlouPythonJiaochengHeji20160905Fix1/index.html
ShiyanlouPythonJiaochengHeji20160905Fix1/css/__init__.py
ShiyanlouPythonJiaochengHeji20160905Fix1/css/annotations.css
ShiyanlouPythonJiaochengHeji20160905Fix1/css/main.css
ShiyanlouPythonJiaochengHeji20160905Fix1/css/normalize.css
ShiyanlouPythonJiaochengHeji20160905Fix1/css/popup.css
ShiyanlouPythonJiaochengHeji20160905Fix1/font/__init__.py
ShiyanlouPythonJiaochengHeji20160905Fix1/font/fontello.eot
ShiyanlouPythonJiaochengHeji20160905Fix1/font/fontello.svg
ShiyanlouPythonJiaochengHeji20160905Fix1/font/fontello.ttf
ShiyanlouPythonJiaochengHeji20160905Fix1/font/fontello.woff
ShiyanlouPythonJiaochengHeji20160905Fix1/img/__init__.py
ShiyanlouPythonJiaochengHeji20160905Fix1/img/annotator-glyph-sprite.png
ShiyanlouPythonJiaochengHeji20160905Fix1/img/annotator-icon-sprite.png
ShiyanlouPythonJiaochengHeji20160905Fix1/img/apple-touch-icon.png
ShiyanlouPythonJiaochengHeji20160905Fix1/img/cancelfullscreen.png
ShiyanlouPythonJiaochengHeji20160905Fix1/img/close.png
ShiyanlouPythonJiaochengHeji20160905Fix1/img/fullscreen.png
ShiyanlouPythonJiaochengHeji20160905Fix1/img/loader.gif
ShiyanlouPythonJiaochengHeji20160905Fix1/img/menu-icon.png
ShiyanlouPythonJiaochengHeji20160905Fix1/img/save.png
ShiyanlouPythonJiaochengHeji20160905Fix1/img/saved.png
ShiyanlouPythonJiaochengHeji20160905Fix1/img/settings-s.png
ShiyanlouPythonJiaochengHeji20160905Fix1/img/settings.png
ShiyanlouPythonJiaochengHeji20160905Fix1/img/star.png
ShiyanlouPythonJiaochengHeji20160905Fix1/js/__init__.py
ShiyanlouPythonJiaochengHeji20160905Fix1/js/epub.js
ShiyanlouPythonJiaochengHeji20160905Fix1/js/epub.min.js
ShiyanlouPythonJiaochengHeji20160905Fix1/js/epub.min.map
ShiyanlouPythonJiaochengHeji20160905Fix1/js/hooks.min.js
shiyanlou_python_jiaocheng_heji_20160905_fix1-2024.3.2.0.dist-info/METADATA
shiyanlou_python_jiaocheng_heji_20160905_fix1-2024.3.2.0.dist-info/WHEEL
shiyanlou_python_jiaocheng_heji_20160905_fix1-2024.3.2.0.dist-info/entry_points.txt
shiyanlou_python_jiaocheng_heji_20160905_fix1-2024.3.2.0.dist-info/top_level.txt
shiyanlou_python_jiaocheng_heji_20160905_fix1-2024.3.2.0.dist-info/RECORD
